weboob/__init__.py
weboob/exceptions.py
weboob/applications/__init__.py
weboob/applications/boobands/__init__.py
weboob/applications/boobands/boobands.py
weboob/applications/boobank/__init__.py
weboob/applications/boobank/boobank.py
weboob/applications/boobathon/__init__.py
weboob/applications/boobathon/boobathon.py
weboob/applications/boobcoming/__init__.py
weboob/applications/boobcoming/boobcoming.py
weboob/applications/boobill/__init__.py
weboob/applications/boobill/boobill.py
weboob/applications/booblyrics/__init__.py
weboob/applications/booblyrics/booblyrics.py
weboob/applications/boobmsg/__init__.py
weboob/applications/boobmsg/boobmsg.py
weboob/applications/boobooks/__init__.py
weboob/applications/boobooks/boobooks.py
weboob/applications/boobsize/__init__.py
weboob/applications/boobsize/boobsize.py
weboob/applications/boobtracker/__init__.py
weboob/applications/boobtracker/boobtracker.py
weboob/applications/boomoney/__init__.py
weboob/applications/boomoney/boomoney.py
weboob/applications/cineoob/__init__.py
weboob/applications/cineoob/cineoob.py
weboob/applications/comparoob/__init__.py
weboob/applications/comparoob/comparoob.py
weboob/applications/cookboob/__init__.py
weboob/applications/cookboob/cookboob.py
weboob/applications/flatboob/__init__.py
weboob/applications/flatboob/flatboob.py
weboob/applications/galleroob/__init__.py
weboob/applications/galleroob/galleroob.py
weboob/applications/geolooc/__init__.py
weboob/applications/geolooc/geolooc.py
weboob/applications/handjoob/__init__.py
weboob/applications/handjoob/handjoob.py
weboob/applications/havedate/__init__.py
weboob/applications/havedate/havedate.py
weboob/applications/monboob/__init__.py
weboob/applications/monboob/monboob.py
weboob/applications/parceloob/__init__.py
weboob/applications/parceloob/parceloob.py
weboob/applications/pastoob/__init__.py
weboob/applications/pastoob/pastoob.py
weboob/applications/radioob/__init__.py
weboob/applications/radioob/radioob.py
weboob-2.0.dist-info/AUTHORS
weboob-2.0.dist-info/COPYING
weboob-2.0.dist-info/COPYING.LESSER
weboob-2.0.dist-info/METADATA
weboob-2.0.dist-info/WHEEL
weboob-2.0.dist-info/entry_points.txt
weboob-2.0.dist-info/top_level.txt
weboob-2.0.dist-info/RECORD
