Metadata-Version: 2.1
Name: weboob
Version: 2.0
Summary: Weboob, Web Outside Of Browsers
Home-page: https://weboob.org/
Author: Romain Bignon
Author-email: weboob@weboob.org
Maintainer: Romain Bignon
Maintainer-email: romain@weboob.org
License: GNU LGPL 3
Platform: UNKNOWN
Classifier: Environment :: Console
Classifier: License :: OSI Approved :: GNU Lesser General Public License v3 or later (LGPLv3+)
Classifier: Programming Language :: Python
Classifier: Programming Language :: Python :: 3
Classifier: Programming Language :: Python :: 3.5
Classifier: Programming Language :: Python :: 3.6
Classifier: Programming Language :: Python :: 3.7
Classifier: Programming Language :: Python :: 3.8
Classifier: Programming Language :: Python
Classifier: Topic :: Communications :: Email
Classifier: Topic :: Internet :: WWW/HTTP
Classifier: Topic :: Internet :: WWW/HTTP :: Browsers
Classifier: Topic :: Software Development :: Libraries :: Application Frameworks
Classifier: Topic :: Software Development :: Libraries :: Python Modules
Classifier: Topic :: Text Processing :: Markup :: HTML
Requires-Python: >=3.5
Requires-Dist: Babel
Requires-Dist: Pillow
Requires-Dist: PyYAML
Requires-Dist: cssselect
Requires-Dist: html2text (>=3.200)
Requires-Dist: lxml
Requires-Dist: python-dateutil
Requires-Dist: requests (>=2.0.0)
Requires-Dist: six
Requires-Dist: unidecode
